pinnsolve/__init__.py
pinnsolve-0.0.1a2.dist-info/METADATA
pinnsolve-0.0.1a2.dist-info/WHEEL
pinnsolve-0.0.1a2.dist-info/licenses/LICENSE
pinnsolve-0.0.1a2.dist-info/RECORD
